[
  { "id_cidade": 3200102, "nomeCidade": "Afonso Cláudio" },
  { "id_cidade": 3200169, "nomeCidade": "Água Doce do Norte" },
  { "id_cidade": 3200136, "nomeCidade": "Águia Branca" },
  { "id_cidade": 3200201, "nomeCidade": "Alegre" },
  { "id_cidade": 3200300, "nomeCidade": "Alfredo Chaves" },
  { "id_cidade": 3200359, "nomeCidade": "Alto Rio Novo" },
  { "id_cidade": 3200409, "nomeCidade": "Anchieta" },
  { "id_cidade": 3200508, "nomeCidade": "Apiacá" },
  { "id_cidade": 3200607, "nomeCidade": "Aracruz" },
  { "id_cidade": 3200706, "nomeCidade": "Atílio Vivacqua" },
  { "id_cidade": 3200805, "nomeCidade": "Baixo Guandu" },
  { "id_cidade": 3200904, "nomeCidade": "Barra de São Francisco" },
  { "id_cidade": 3201001, "nomeCidade": "Boa Esperança" },
  { "id_cidade": 3201100, "nomeCidade": "Bom Jesus do Norte" },
  { "id_cidade": 3201159, "nomeCidade": "Brejetuba" },
  { "id_cidade": 3201209, "nomeCidade": "Cachoeiro de Itapemirim" },
  { "id_cidade": 3201308, "nomeCidade": "Cariacica" },
  { "id_cidade": 3201407, "nomeCidade": "Castelo" },
  { "id_cidade": 3201506, "nomeCidade": "Colatina" },
  { "id_cidade": 3201605, "nomeCidade": "Conceição da Barra" },
  { "id_cidade": 3201704, "nomeCidade": "Conceição do Castelo" },
  { "id_cidade": 3201803, "nomeCidade": "Divino de São Lourenço" },
  { "id_cidade": 3201902, "nomeCidade": "Domingos Martins" },
  { "id_cidade": 3202009, "nomeCidade": "Dores do Rio Preto" },
  { "id_cidade": 3202108, "nomeCidade": "Ecoporanga" },
  { "id_cidade": 3202207, "nomeCidade": "Fundão" },
  { "id_cidade": 3202256, "nomeCidade": "Governador Lindenberg" },
  { "id_cidade": 3202306, "nomeCidade": "Guaçuí" },
  { "id_cidade": 3202405, "nomeCidade": "Guarapari" },
  { "id_cidade": 3202454, "nomeCidade": "Ibatiba" },
  { "id_cidade": 3202504, "nomeCidade": "Ibiraçu" },
  { "id_cidade": 3202553, "nomeCidade": "Ibitirama" },
  { "id_cidade": 3202603, "nomeCidade": "Iconha" },
  { "id_cidade": 3202652, "nomeCidade": "Irupi" },
  { "id_cidade": 3202702, "nomeCidade": "Itaguaçu" },
  { "id_cidade": 3202801, "nomeCidade": "Itapemirim" },
  { "id_cidade": 3202900, "nomeCidade": "Itarana" },
  { "id_cidade": 3203007, "nomeCidade": "Iúna" },
  { "id_cidade": 3203056, "nomeCidade": "Jaguaré" },
  { "id_cidade": 3203106, "nomeCidade": "Jerônimo Monteiro" },
  { "id_cidade": 3203130, "nomeCidade": "João Neiva" },
  { "id_cidade": 3203163, "nomeCidade": "Laranja da Terra" },
  { "id_cidade": 3203205, "nomeCidade": "Linhares" },
  { "id_cidade": 3203304, "nomeCidade": "Mantenópolis" },
  { "id_cidade": 3203320, "nomeCidade": "Marataízes" },
  { "id_cidade": 3203346, "nomeCidade": "Marechal Floriano" },
  { "id_cidade": 3203353, "nomeCidade": "Marilândia" },
  { "id_cidade": 3203403, "nomeCidade": "Mimoso do Sul" },
  { "id_cidade": 3203502, "nomeCidade": "Montanha" },
  { "id_cidade": 3203601, "nomeCidade": "Mucurici" },
  { "id_cidade": 3203700, "nomeCidade": "Muniz Freire" },
  { "id_cidade": 3203809, "nomeCidade": "Muqui" },
  { "id_cidade": 3203908, "nomeCidade": "Nova Venécia" },
  { "id_cidade": 3204005, "nomeCidade": "Pancas" },
  { "id_cidade": 3204054, "nomeCidade": "Pedro Canário" },
  { "id_cidade": 3204104, "nomeCidade": "Pinheiros" },
  { "id_cidade": 3204203, "nomeCidade": "Piúma" },
  { "id_cidade": 3204252, "nomeCidade": "Ponto Belo" },
  { "id_cidade": 3204302, "nomeCidade": "Presidente Kennedy" },
  { "id_cidade": 3204351, "nomeCidade": "Rio Bananal" },
  { "id_cidade": 3204401, "nomeCidade": "Rio Novo do Sul" },
  { "id_cidade": 3204500, "nomeCidade": "Santa Leopoldina" },
  { "id_cidade": 3204559, "nomeCidade": "Santa Maria de Jetibá" },
  { "id_cidade": 3204609, "nomeCidade": "Santa Teresa" },
  { "id_cidade": 3204658, "nomeCidade": "São Domingos do Norte" },
  { "id_cidade": 3204708, "nomeCidade": "São Gabriel da Palha" },
  { "id_cidade": 3204807, "nomeCidade": "São José do Calçado" },
  { "id_cidade": 3204906, "nomeCidade": "São Mateus" },
  { "id_cidade": 3204955, "nomeCidade": "São Roque do Canaã" },
  { "id_cidade": 3205002, "nomeCidade": "Serra" },
  { "id_cidade": 3205010, "nomeCidade": "Sooretama" },
  { "id_cidade": 3205036, "nomeCidade": "Vargem Alta" },
  { "id_cidade": 3205069, "nomeCidade": "Venda Nova do Imigrante" },
  { "id_cidade": 3205101, "nomeCidade": "Viana" },
  { "id_cidade": 3205150, "nomeCidade": "Vila Pavão" },
  { "id_cidade": 3205176, "nomeCidade": "Vila Valério" },
  { "id_cidade": 3205200, "nomeCidade": "Vila Velha" },
  { "id_cidade": 3205309, "nomeCidade": "Vitória" }
]
